gitlab_client/__init__.py
gitlab_client/config.py
gitlab_client/exceptions.py
gitlab_client/gitlab_client.py
gitlab_v4-0.0.7.dist-info/METADATA
gitlab_v4-0.0.7.dist-info/WHEEL
gitlab_v4-0.0.7.dist-info/top_level.txt
gitlab_v4-0.0.7.dist-info/RECORD
