Metadata-Version: 2.1
Name: gitlab-v4
Version: 0.0.7
Summary: Wrapper for Gitlab API v4
Home-page: https://gitlab.com/abhaykoduru/gitlab_client
Author: Abhay Santhosh Koduru
Author-email: k.abhaysanthosh@gmail.com
License: MIT
Platform: UNKNOWN
Classifier: Intended Audience :: Developers
Classifier: Programming Language :: Python :: 3.0
Classifier: Programming Language :: Python :: 3.8
Classifier: Programming Language :: Python :: 3.9
Classifier: Operating System :: OS Independent
Classifier: License :: OSI Approved :: MIT License
Requires-Dist: certifi (==2021.5.30)
Requires-Dist: charset-normalizer (==2.0.4)
Requires-Dist: idna (==3.2)
Requires-Dist: requests (==2.26.0)
Requires-Dist: urllib3 (==1.26.6)
